viggolocalv2/__init__.py
viggolocalv2/resources.py
viggolocalv2/subsystem/__init__.py
viggolocalv2/subsystem/common/__init__.py
viggolocalv2/subsystem/common/endereco/__init__.py
viggolocalv2/subsystem/common/endereco/resource.py
viggolocalv2/subsystem/parametrizacao/__init__.py
viggolocalv2/subsystem/parametrizacao/localidade/__init__.py
viggolocalv2/subsystem/parametrizacao/localidade/mesorregiao/__init__.py
viggolocalv2/subsystem/parametrizacao/localidade/mesorregiao/resource.py
viggolocalv2/subsystem/parametrizacao/localidade/microrregiao/__init__.py
viggolocalv2/subsystem/parametrizacao/localidade/microrregiao/resource.py
viggolocalv2/subsystem/parametrizacao/localidade/municipio/__init__.py
viggolocalv2/subsystem/parametrizacao/localidade/municipio/resource.py
viggolocalv2/subsystem/parametrizacao/localidade/pais/__init__.py
viggolocalv2/subsystem/parametrizacao/localidade/pais/resource.py
viggolocalv2/subsystem/parametrizacao/localidade/regiao/__init__.py
viggolocalv2/subsystem/parametrizacao/localidade/regiao/resource.py
viggolocalv2/subsystem/parametrizacao/localidade/uf/__init__.py
viggolocalv2/subsystem/parametrizacao/localidade/uf/resource.py
viggolocalv2/subsystem/sysadmin/__init__.py
viggolocalv2/subsystem/sysadmin/ibge_sync/__init__.py
viggolocalv2/subsystem/sysadmin/ibge_sync/manager.py
viggolocalv2/subsystem/sysadmin/ibge_sync/resource.py
viggolocalv2-1.0.2.dist-info/licenses/AUTHORS
viggolocalv2-1.0.2.dist-info/METADATA
viggolocalv2-1.0.2.dist-info/WHEEL
viggolocalv2-1.0.2.dist-info/top_level.txt
viggolocalv2-1.0.2.dist-info/RECORD
