Metadata-Version: 2.4
Name: viggolocalv2
Version: 1.0.2
Summary: ViggoLocalV2 backend Flask REST service
License-File: AUTHORS
Requires-Dist: viggocorev2<2.0.0,>=1.0.0
Requires-Dist: flask-cors
Dynamic: license-file
Dynamic: requires-dist
Dynamic: summary
